fedextrack/__init__.py
fedextrack/classes/__init__.py
fedextrack/classes/fedex.py
fedextrack/classes/http.py
fedextrack-0.9.0.dist-info/METADATA
fedextrack-0.9.0.dist-info/WHEEL
fedextrack-0.9.0.dist-info/licenses/LICENSE
fedextrack-0.9.0.dist-info/RECORD
