Metadata-Version: 2.1
Name: fedextrack
Version: 0.9.0
Summary: Simple Python wrapper to fetch data from FedEx Tracking API
Project-URL: Homepage, https://kumig.it/kumitterer/fedextrack
Project-URL: Bug Tracker, https://kumig.it/kumitterer/fedextrack/issues
Author-email: Kumi Mitterer <fedextrack@kumi.email>
License: Copyright (c) 2023 Kumi Mitterer <fedextrack@kumi.email>
License-File: LICENSE
Classifier: License :: OSI Approved :: MIT License
Classifier: Operating System :: OS Independent
Classifier: Programming Language :: Python :: 3
Requires-Python: >=3.10
